Metadata-Version: 2.1
Name: file-light
Version: 0.3
Summary: Gaussian and Binomial distributions
Home-page: UNKNOWN
Author-email: kassas20@mail.ru
License: UNKNOWN
Platform: UNKNOWN
